eth/__init__.py
py_eth-0.1.1.dist-info/DESCRIPTION.rst
py_eth-0.1.1.dist-info/METADATA
py_eth-0.1.1.dist-info/RECORD
py_eth-0.1.1.dist-info/WHEEL
py_eth-0.1.1.dist-info/metadata.json
py_eth-0.1.1.dist-info/top_level.txt
